cardanopythonlib/__init__.py
cardanopythonlib/base.py
cardanopythonlib/config/cardano_config.ini
cardanopythonlib/data_utils.py
cardanopythonlib/datatypes/__init__.py
cardanopythonlib/datatypes/exception.py
cardanopythonlib/datatypes/hash.py
cardanopythonlib/datatypes/nativescript.py
cardanopythonlib/datatypes/plutus.py
cardanopythonlib/datatypes/serialization.py
cardanopythonlib/destination.py
cardanopythonlib/keys.py
cardanopythonlib/mint.py
cardanopythonlib/path_utils.py
cardanopythonlib/schemas.py
cardanopythonlib/source.py
cardanopythonlib/starter.py
cardanopythonlib-1.2.dist-info/LICENSE
cardanopythonlib-1.2.dist-info/METADATA
cardanopythonlib-1.2.dist-info/WHEEL
cardanopythonlib-1.2.dist-info/RECORD
