Metadata-Version: 2.1
Name: cardanopythonlib
Version: 1.2
Summary: Cardano Python lib to interact with the blockchain
Home-page: https://github.com/larestrepo/CardanoPythonLib
License: Apache-2.0
Keywords: cardano,blockchain,python,backend
Author: Moxie
Author-email: luis.restrepo@ayllu.io
Requires-Python: >=3.9,<4.0
Classifier: License :: OSI Approved :: Apache Software License
Classifier: Programming Language :: Python :: 3
Classifier: Programming Language :: Python :: 3.9
Classifier: Programming Language :: Python :: 3.10
Classifier: Programming Language :: Python :: 3.11
Requires-Dist: cbor2 (>=5.4.6,<6.0.0)
Requires-Dist: cerberus (>=1.3.4,<2.0.0)
Requires-Dist: pprintpp (>=0.4.0,<0.5.0)
Requires-Dist: pynacl (>=1.5.0,<2.0.0)
Requires-Dist: typeguard (>=2.13.3,<3.0.0)
Project-URL: Repository, https://github.com/larestrepo/CardanoPythonLib
